arango_cti_processor/__init__.py
arango_cti_processor/__main__.py
arango_cti_processor/config.py
arango_cti_processor/managers/__init__.py
arango_cti_processor/managers/base_manager.py
arango_cti_processor/managers/capec_attack.py
arango_cti_processor/managers/cwe_capec.py
arango_cti_processor/managers/technique_tactic.py
arango_cti_processor/tools/utils.py
arango_cti_processor-1.0.7.dist-info/METADATA
arango_cti_processor-1.0.7.dist-info/WHEEL
arango_cti_processor-1.0.7.dist-info/entry_points.txt
arango_cti_processor-1.0.7.dist-info/licenses/LICENSE
arango_cti_processor-1.0.7.dist-info/RECORD
