Metadata-Version: 2.4
Name: arango_cti_processor
Version: 1.0.7
Summary: A small script that creates relationships between common CTI knowledge-bases in STIX 2.1 format.
Project-URL: Homepage, https://github.com/muchdogesec/arango_cti_processor
Project-URL: Issues, https://github.com/muchdogesec/arango_cti_processor/issues
Project-URL: dogesec HQ, https://dogesec.com
Author: dogesec
Maintainer: dogesec
License-File: LICENSE
Classifier: License :: OSI Approved :: Apache Software License
Classifier: Operating System :: OS Independent
Classifier: Programming Language :: Python :: 3
Requires-Python: >=3.9
Requires-Dist: jsonschema>=4.22.0; python_version >= '3.8'
Requires-Dist: python-arango>=8.1.3; python_version >= '3.8'
Requires-Dist: requests>=2.32.4; python_version >= '3.7'
Requires-Dist: stix2
Requires-Dist: stix2arango
Requires-Dist: tqdm>=4.66.4; python_version >= '3.7'
